flask_native_stubs/__init__.py
flask_native_stubs/_safe_exit.py
flask_native_stubs/api/__init__.py
flask_native_stubs/api/client_side.py
flask_native_stubs/api/daemon_side.py
flask_native_stubs/api/server_side.py
flask_native_stubs/app.py
flask_native_stubs/config.py
flask_native_stubs/delegator.py
flask_native_stubs/protocol.py
flask_native_stubs/request.py
flask_native_stubs/response.py
flask_native_stubs/stubgen/__init__.py
flask_native_stubs/stubgen/func_parser.py
flask_native_stubs/stubgen/general.py
flask_native_stubs/stubgen/route.py
flask_native_stubs/stubgen/runtime_collector.py
flask_native_stubs/stubgen/stubgen.py
flask_native_stubs-0.4.4.dist-info/LICENSE
flask_native_stubs-0.4.4.dist-info/WHEEL
flask_native_stubs-0.4.4.dist-info/METADATA
flask_native_stubs-0.4.4.dist-info/RECORD
