Metadata-Version: 2.1
Name: flask-native-stubs
Version: 0.4.4
Summary: Call flask decorated functions like native ones.
Home-page: https://github.com/likianta/flask-native-stubs
License: MIT
Author: Likianta
Author-email: likianta@foxmail.com
Requires-Python: >=3.8,<4.0
Classifier: License :: OSI Approved :: MIT License
Classifier: Programming Language :: Python :: 3
Classifier: Programming Language :: Python :: 3.8
Classifier: Programming Language :: Python :: 3.9
Classifier: Programming Language :: Python :: 3.10
Classifier: Programming Language :: Python :: 3.11
Requires-Dist: flask
Requires-Dist: requests
Requires-Dist: urllib3
